csd/__init__.py
csd/methods.py
csd/metrics.py
csd-1.0.0.dist-info/LICENSE
csd-1.0.0.dist-info/METADATA
csd-1.0.0.dist-info/WHEEL
csd-1.0.0.dist-info/top_level.txt
csd-1.0.0.dist-info/RECORD
