Metadata-Version: 2.1
Name: csd
Version: 1.0.0
Summary: (Constrained) subgroup discovery
Author-email: Jakob Bach <jakob.bach.ka@gmail.com>
Project-URL: Homepage, https://github.com/Jakob-Bach/Constrained-Subgroup-Discovery/tree/main/csd_package
Project-URL: Issues, https://github.com/Jakob-Bach/Constrained-Subgroup-Discovery/issues
Keywords: subgroup discovery,constraints,feature selection,alternative subgroup descriptions
Classifier: Programming Language :: Python :: 3
Classifier: License :: OSI Approved :: MIT License
Classifier: Operating System :: OS Independent
Requires-Python: >=3.8
License-File: LICENSE
Requires-Dist: numpy >=1.24.4
Requires-Dist: ortools >=9.7.2996
Requires-Dist: pandas >=2.0.3
Requires-Dist: z3-solver >=4.12.2.0
